{"id":46796664,"name":"D/D Savant Copernicus","type":"Pendulum Effect Monster","frameType":"effect_pendulum","desc":"[ Pendulum Effect ] \n[ Monster Effect ] If this card is Normal or Special Summoned: You can send 1 \"D/D\" or \"Dark Contract\" card from your Deck to the GY, except \"D/D Savant Copernicus\". You can only use this effect of \"D/D Savant Copernicus\" once per turn.","pend_desc":"You cannot Pendulum Summon monsters, except \"D/D\" monsters. This effect cannot be negated. Once, while this card is in your Pendulum Zone, you can negate an activated Spell effect that would inflict damage to you, then destroy this card.","monster_desc":"If this card is Normal or Special Summoned: You can send 1 \"D/D\" or \"Dark Contract\" card from your Deck to the GY, except \"D/D Savant Copernicus\". You can only use this effect of \"D/D Savant Copernicus\" once per turn.","atk":0,"def":0,"level":4,"race":"Fiend","attribute":"DARK","archetype":"D/D","scale":1,"card_sets":[{"set_name":"Ghosts From the Past: The 2nd Haunting","set_code":"GFP2-EN076","set_rarity":"Ultra Rare","set_rarity_code":"(UR)","set_price":"0.97"},{"set_name":"Pendulum Domination Structure Deck","set_code":"SDPD-EN003","set_rarity":"Common","set_rarity_code":"(C)","set_price":"3.23"}],"card_images":[{"id":46796664,"image_url":"https://images.ygoprodeck.com/images/cards/46796664.jpg","image_url_small":"https://images.ygoprodeck.com/images/cards_small/46796664.jpg","image_url_cropped":"https://images.ygoprodeck.com/images/cards_cropped/46796664.jpg"}],"card_prices":[{"cardmarket_price":"0.26","tcgplayer_price":"0.19","ebay_price":"1.50","amazon_price":"0.75","coolstuffinc_price":"0.99"}]}